truster/__init__.py
truster/bcolors.py
truster/cluster.py
truster/experiment.py
truster/jobHandler.py
truster/sample.py
truster/__pycache__/__init__.cpython-37.pyc
truster/__pycache__/bcolors.cpython-37.pyc
truster/__pycache__/jobHandler.cpython-37.pyc
truster/py_scripts/filterUMIs
truster/py_scripts/plotTEexpression
truster/py_scripts/plotVelocity
truster/r_scripts/get_clusters.R
truster/r_scripts/merge_samples.R
truster/r_scripts/normalize_TEexpression.R
truster/r_scripts/plot_TEexpression.R
truster-0.1.1.data/scripts/filterUMIs
truster-0.1.1.dist-info/METADATA
truster-0.1.1.dist-info/WHEEL
truster-0.1.1.dist-info/top_level.txt
truster-0.1.1.dist-info/RECORD
