Metadata-Version: 2.1
Name: truster
Version: 0.1.1
Summary: Analyse transposons expression in single cell data.
Home-page: https://github.com/ra7555ga-s/trusTEr
Author: Raquel Garza
Author-email: raquelgarza95@gmail.com
License: UNKNOWN
Platform: UNKNOWN
Classifier: Topic :: Scientific/Engineering :: Bio-Informatics
